cgstats/__init__.py
cgstats/cli.py
cgstats/initialize.py
cgstats/settings.py
cgstats/xparseunaligned.py
cgstats/analysis/__init__.py
cgstats/analysis/api.py
cgstats/analysis/cli.py
cgstats/analysis/export.py
cgstats/analysis/mip.py
cgstats/analysis/models.py
cgstats/db/__init__.py
cgstats/db/api.py
cgstats/db/cli.py
cgstats/db/models.py
cgstats/db/parse.py
cgstats/db/xparse.py
cgstats/utils/__init__.py
cgstats/utils/stats.py
cgstats/utils/utils.py
cgstats/utils/xstats.py
cgstats-1.0.1.dist-info/DESCRIPTION.rst
cgstats-1.0.1.dist-info/METADATA
cgstats-1.0.1.dist-info/RECORD
cgstats-1.0.1.dist-info/WHEEL
cgstats-1.0.1.dist-info/entry_points.txt
cgstats-1.0.1.dist-info/metadata.json
cgstats-1.0.1.dist-info/top_level.txt
clinstatsweb/__init__.py
clinstatsweb/app.py
