Metadata-Version: 2.0
Name: cgstats
Version: 1.0.1
Summary: Models and access to cgstats
Home-page: UNKNOWN
Author: Kenny Billiau
Author-email: kenny.billiau@scilifelab.se
License: MIT
Platform: any
Classifier: Development Status :: 3 - Alpha
Classifier: Intended Audience :: Science/Research
Classifier: Topic :: Software Development
Classifier: Topic :: Scientific/Engineering :: Bio-Informatics
Classifier: License :: OSI Approved :: MIT License
Classifier: Operating System :: OS Independent
Classifier: Programming Language :: Python :: 2
Classifier: Programming Language :: Python :: 2.7
Classifier: Programming Language :: Python :: 3
Classifier: Programming Language :: Python :: 3.3
Classifier: Programming Language :: Python :: 3.4
Classifier: Environment :: Console
Requires-Dist: Flask
Requires-Dist: Flask-Alchy
Requires-Dist: Flask-Bootstrap
Requires-Dist: PyYAML
Requires-Dist: SQLAlchemy
Requires-Dist: alchy
Requires-Dist: alembic
Requires-Dist: bs4
Requires-Dist: bumpversion
Requires-Dist: click
Requires-Dist: path.py
Requires-Dist: pymysql
Requires-Dist: pytest
Requires-Dist: wheel
